codex/__init__.py
codex/client.py
codex/config.py
codex/event.py
codex/exec.py
codex/native.py
codex/protocol/_base_model.py
codex/protocol/types.py
codex/py.typed
codex_native/__init__.py
codex_native/codex_native.abi3.so
codex_python-0.3.0.dist-info/METADATA
codex_python-0.3.0.dist-info/WHEEL
codex_python-0.3.0.dist-info/licenses/LICENSE
codex_python-0.3.0.dist-info/RECORD
