Metadata-Version: 2.4
Name: codex-python
Version: 0.3.0
Classifier: Programming Language :: Python :: 3
Classifier: Programming Language :: Python :: 3 :: Only
Classifier: Programming Language :: Python :: 3.13
Classifier: License :: OSI Approved :: MIT License
Classifier: Typing :: Typed
Classifier: Operating System :: OS Independent
Requires-Dist: pydantic>=2.11.7
License-File: LICENSE
Summary: A minimal Python library scaffold for codex-python
Keywords: codex,library,scaffold
Requires-Python: >=3.12
Project-URL: Homepage, https://github.com/gersmann/codex-python
Project-URL: Repository, https://github.com/gersmann/codex-python
Project-URL: Issues, https://github.com/gersmann/codex-python/issues
